LICENSE.md
README.md
pyproject.toml
requirements.txt
src/erebus/__init__.py
src/erebus/erebus.py
src/erebus/frame_normalized_pca.py
src/erebus/individual_fit.py
src/erebus/individual_fit_results.py
src/erebus/joint_fit.py
src/erebus/joint_fit_results.py
src/erebus/mcmc_model.py
src/erebus/photometry_data.py
src/erebus/plotting.py
src/erebus/wrapped_fits.py
src/erebus/utility/__init__.py
src/erebus/utility/aperture_photometry_utils.py
src/erebus/utility/bayesian_parameter.py
src/erebus/utility/fits_file_utils.py
src/erebus/utility/h5_serializable_file.py
src/erebus/utility/planet.py
src/erebus/utility/run_cfg.py
src/erebus/utility/utils.py
src/erebus_exoplanet.egg-info/PKG-INFO
src/erebus_exoplanet.egg-info/SOURCES.txt
src/erebus_exoplanet.egg-info/dependency_links.txt
src/erebus_exoplanet.egg-info/requires.txt
src/erebus_exoplanet.egg-info/top_level.txt