Metadata-Version: 2.4
Name: erebus_exoplanet
Version: 0.7.1
Summary: An exoplanet eclipse depth tool
Author-email: Nicholas Connors <nicholas.connors@umontreal.ca>
License-Expression: MIT
Project-URL: Homepage, https://github.com/nicholasconnors/erebus
Project-URL: Documentation, https://nicholasconnors.github.io/erebus
Project-URL: Issues, https://github.com/nicholasconnors/erebus/issues
Classifier: Programming Language :: Python :: 3
Requires-Python: >=3.10
License-File: LICENSE.md
Requires-Dist: astropy==6.1.3
Requires-Dist: batman_package==2.4.9
Requires-Dist: corner==2.2.2
Requires-Dist: emcee==3.1.6
Requires-Dist: h5py==3.12.1
Requires-Dist: jwst==1.15.1
Requires-Dist: matplotlib==3.10.3
Requires-Dist: numpy==1.26.4
Requires-Dist: pydantic==2.11.5
Requires-Dist: pydantic_yaml==1.4.0
Requires-Dist: scikit_learn==1.6.1
Requires-Dist: scipy==1.15.3
Requires-Dist: uncertainties==3.2.2
Requires-Dist: tqdm==4.66.4
Requires-Dist: dill==0.3.8
Dynamic: license-file
